setup.py
musicrepair/__init__.py
musicrepair/command_line.py
musicrepair/config.ini
musicrepair.egg-info/PKG-INFO
musicrepair.egg-info/SOURCES.txt
musicrepair.egg-info/dependency_links.txt
musicrepair.egg-info/entry_points.txt
musicrepair.egg-info/requires.txt
musicrepair.egg-info/top_level.txt