Metadata-Version: 1.0
Name: musicrepair
Version: 6.2.1
Summary: Lets you repair your music files by adding metadata and album art
Home-page: https://github.com/lakshaykalbhor/musicrepair
Author: Lakshay Kalbhor
Author-email: lakshaykalbhor@gmail.com
License: MIT
Platform: UNKNOWN
